squashblame.py
git_squash_blame-0.1.0.dist-info/entry_points.txt
git_squash_blame-0.1.0.dist-info/WHEEL
git_squash_blame-0.1.0.dist-info/METADATA
git_squash_blame-0.1.0.dist-info/RECORD
